workbench_bridges/__init__.py
workbench_bridges/api/__init__.py
workbench_bridges/api/df_store.py
workbench_bridges/api/inference_store.py
workbench_bridges/api/parameter_store.py
workbench_bridges/aws/sagemaker_session.py
workbench_bridges/endpoints/fast_inference.py
workbench_bridges/utils/athena_utils.py
workbench_bridges/utils/aws_utils.py
workbench_bridges/utils/datetime_utils.py
workbench_bridges/utils/execution_environment.py
workbench_bridges/utils/glue_utils.py
workbench_bridges/utils/json_utils.py
workbench_bridges/utils/logger.py
workbench_bridges-0.1.16.dist-info/licenses/LICENSE
workbench_bridges-0.1.16.dist-info/METADATA
workbench_bridges-0.1.16.dist-info/WHEEL
workbench_bridges-0.1.16.dist-info/top_level.txt
workbench_bridges-0.1.16.dist-info/RECORD
