Metadata-Version: 2.4
Name: workbench-bridges
Version: 0.1.16
Summary: Workbench Bridges: End User Application Bridges to Workbench/AWS
Author-email: SuperCowPowers LLC <support@supercowpowers.com>
License: MIT
Project-URL: Homepage, https://github.com/SuperCowPowers/workbench-bridges
Keywords: SageMaker,Machine Learning,AWS,Python,Utilities
Classifier: Development Status :: 4 - Beta
Classifier: License :: OSI Approved :: MIT License
Classifier: Programming Language :: Python :: 3.10
Classifier: Programming Language :: Python :: 3.11
Classifier: Programming Language :: Python :: 3.12
Classifier: Topic :: Scientific/Engineering
Requires-Python: >=3.9
License-File: LICENSE
Requires-Dist: boto3>=1.28.76
Requires-Dist: botocore>=1.31.76
Requires-Dist: awswrangler>=3.4.0
Requires-Dist: sagemaker<3.0,>=2.143
Requires-Dist: requests>=2.26.0
Dynamic: license-file
